brush/__init__.py
brush/__main__.py
brush/cli.py
brush/comb.py
brush/models.py
brush/stores.py
brush/sweep.py
brush/uimethods.py
brush/web.py
brush/static/css/bootstrap-theme.min.css
brush/static/css/bootstrap.min.css
brush/static/css/style.css
brush/static/fonts/glyphicons-halflings-regular.eot
brush/static/fonts/glyphicons-halflings-regular.svg
brush/static/fonts/glyphicons-halflings-regular.ttf
brush/static/fonts/glyphicons-halflings-regular.woff
brush/static/fonts/glyphicons-halflings-regular.woff2
brush/static/img/brush.png
brush/static/img/brush.svg
brush/static/js/EventEmitter.js
brush/static/js/components.js
brush/static/js/index.js
brush/static/js/routes.js
brush/static/js/store.js
brush/static/js/util.js
brush/templates/index.html
brush/templates/vue/app.html
brush/templates/vue/chart.html
brush/templates/vue/charts-route.html
brush/templates/vue/current-value.html
brush/templates/vue/dashboard.html
brush/templates/vue/download-route.html
brush/templates/vue/navbar.html
brush/templates/vue/status-route.html
brush-1.2.0.dist-info/DESCRIPTION.rst
brush-1.2.0.dist-info/METADATA
brush-1.2.0.dist-info/RECORD
brush-1.2.0.dist-info/WHEEL
brush-1.2.0.dist-info/entry_points.txt
brush-1.2.0.dist-info/metadata.json
brush-1.2.0.dist-info/top_level.txt
