Metadata-Version: 2.0
Name: brush
Version: 1.2.0
Summary: Monitor and log data from Menlo Systems optical frequency combs
Home-page: https://bitbucket.org/iontrapgroup/brush
Author: Michael V. DePalatis
Author-email: depalatis@phys.au.dk
License: MIT
Keywords: physics science optics data acquisition frequency comb
Platform: UNKNOWN
Classifier: Intended Audience :: Science/Research
Classifier: Topic :: Scientific/Engineering :: Physics
Classifier: License :: OSI Approved :: MIT License
Requires-Dist: pytz
Requires-Dist: six
Requires-Dist: sqlalchemy (>=1)
Requires-Dist: tornado (>=4.2.1)
Requires-Dist: tornadose (>=0.3)
Requires-Dist: webassets
